{
  "module_name": "lopcodes.c",
  "hash_id": "45b860dd3b7fdeda516acc02fc2a994e2dbcf8086dcceb37450637db191fdbf2",
  "original_prompt": "Ingested from zfs-2.2.2/module/lua/lopcodes.c",
  "human_readable_source": " \n\n\n#define lopcodes_c\n#define LUA_CORE\n\n\n#include \"lopcodes.h\"\n\n\n \n\nLUAI_DDEF const char *const luaP_opnames[NUM_OPCODES+1] = {\n  \"MOVE\",\n  \"LOADK\",\n  \"LOADKX\",\n  \"LOADBOOL\",\n  \"LOADNIL\",\n  \"GETUPVAL\",\n  \"GETTABUP\",\n  \"GETTABLE\",\n  \"SETTABUP\",\n  \"SETUPVAL\",\n  \"SETTABLE\",\n  \"NEWTABLE\",\n  \"SELF\",\n  \"ADD\",\n  \"SUB\",\n  \"MUL\",\n  \"DIV\",\n  \"MOD\",\n  \"POW\",\n  \"UNM\",\n  \"NOT\",\n  \"LEN\",\n  \"CONCAT\",\n  \"JMP\",\n  \"EQ\",\n  \"LT\",\n  \"LE\",\n  \"TEST\",\n  \"TESTSET\",\n  \"CALL\",\n  \"TAILCALL\",\n  \"RETURN\",\n  \"FORLOOP\",\n  \"FORPREP\",\n  \"TFORCALL\",\n  \"TFORLOOP\",\n  \"SETLIST\",\n  \"CLOSURE\",\n  \"VARARG\",\n  \"EXTRAARG\",\n  NULL\n};\n\n\n#define opmode(t,a,b,c,m) (((t)<<7) | ((a)<<6) | ((b)<<4) | ((c)<<2) | (m))\n\nLUAI_DDEF const lu_byte luaP_opmodes[NUM_OPCODES] = {\n \n  opmode(0, 1, OpArgR, OpArgN, iABC)\t\t \n ,opmode(0, 1, OpArgK, OpArgN, iABx)\t\t \n ,opmode(0, 1, OpArgN, OpArgN, iABx)\t\t \n ,opmode(0, 1, OpArgU, OpArgU, iABC)\t\t \n ,opmode(0, 1, OpArgU, OpArgN, iABC)\t\t \n ,opmode(0, 1, OpArgU, OpArgN, iABC)\t\t \n ,opmode(0, 1, OpArgU, OpArgK, iABC)\t\t \n ,opmode(0, 1, OpArgR, OpArgK, iABC)\t\t \n ,opmode(0, 0, OpArgK, OpArgK, iABC)\t\t \n ,opmode(0, 0, OpArgU, OpArgN, iABC)\t\t \n ,opmode(0, 0, OpArgK, OpArgK, iABC)\t\t \n ,opmode(0, 1, OpArgU, OpArgU, iABC)\t\t \n ,opmode(0, 1, OpArgR, OpArgK, iABC)\t\t \n ,opmode(0, 1, OpArgK, OpArgK, iABC)\t\t \n ,opmode(0, 1, OpArgK, OpArgK, iABC)\t\t \n ,opmode(0, 1, OpArgK, OpArgK, iABC)\t\t \n ,opmode(0, 1, OpArgK, OpArgK, iABC)\t\t \n ,opmode(0, 1, OpArgK, OpArgK, iABC)\t\t \n ,opmode(0, 1, OpArgK, OpArgK, iABC)\t\t \n ,opmode(0, 1, OpArgR, OpArgN, iABC)\t\t \n ,opmode(0, 1, OpArgR, OpArgN, iABC)\t\t \n ,opmode(0, 1, OpArgR, OpArgN, iABC)\t\t \n ,opmode(0, 1, OpArgR, OpArgR, iABC)\t\t \n ,opmode(0, 0, OpArgR, OpArgN, iAsBx)\t\t \n ,opmode(1, 0, OpArgK, OpArgK, iABC)\t\t \n ,opmode(1, 0, OpArgK, OpArgK, iABC)\t\t \n ,opmode(1, 0, OpArgK, OpArgK, iABC)\t\t \n ,opmode(1, 0, OpArgN, OpArgU, iABC)\t\t \n ,opmode(1, 1, OpArgR, OpArgU, iABC)\t\t \n ,opmode(0, 1, OpArgU, OpArgU, iABC)\t\t \n ,opmode(0, 1, OpArgU, OpArgU, iABC)\t\t \n ,opmode(0, 0, OpArgU, OpArgN, iABC)\t\t \n ,opmode(0, 1, OpArgR, OpArgN, iAsBx)\t\t \n ,opmode(0, 1, OpArgR, OpArgN, iAsBx)\t\t \n ,opmode(0, 0, OpArgN, OpArgU, iABC)\t\t \n ,opmode(0, 1, OpArgR, OpArgN, iAsBx)\t\t \n ,opmode(0, 0, OpArgU, OpArgU, iABC)\t\t \n ,opmode(0, 1, OpArgU, OpArgN, iABx)\t\t \n ,opmode(0, 1, OpArgU, OpArgN, iABC)\t\t \n ,opmode(0, 0, OpArgU, OpArgU, iAx)\t\t \n};\n",
  "logic_map": {},
  "failure_modes": [],
  "crash_correlation_map": {}
}